<?xml version="1.0" encoding="UTF-8" standalone="yes"?>
<worksheet xmlns="http://schemas.openxmlformats.org/spreadsheetml/2006/main" xmlns:r="http://schemas.openxmlformats.org/officeDocument/2006/relationships" xmlns:mc="http://schemas.openxmlformats.org/markup-compatibility/2006" mc:Ignorable="x14ac" xmlns:x14ac="http://schemas.microsoft.com/office/spreadsheetml/2009/9/ac"><sheetPr><tabColor theme="6"/></sheetPr><dimension ref="A1:G1"/><sheetViews><sheetView zoomScale="80" zoomScaleNormal="80" workbookViewId="0"><pane xSplit="2" ySplit="1" topLeftCell="C2" activePane="bottomRight" state="frozen"/><selection pane="topRight" activeCell="C1" sqref="C1"/><selection pane="bottomLeft" activeCell="A2" sqref="A2"/><selection pane="bottomRight"/></sheetView></sheetViews><sheetFormatPr defaultRowHeight="15" x14ac:dyDescent="0.25"/><cols><col min="1" max="1" width="15.7109375" style="2" bestFit="1" customWidth="1"/><col min="2" max="2" width="19.140625" style="6" bestFit="1" customWidth="1"/><col min="3" max="3" width="10.85546875" style="6" bestFit="1" customWidth="1"/><col min="4" max="4" width="21.5703125" style="6" bestFit="1" customWidth="1"/><col min="5" max="5" width="21.28515625" style="6" bestFit="1" customWidth="1"/><col min="6" max="6" width="14.5703125" style="8" bestFit="1" customWidth="1"/><col min="7" max="7" width="15.140625" style="8" bestFit="1" customWidth="1"/></cols><sheetData><row r="1" spans="1:7" s="1" customFormat="1" x14ac:dyDescent="0.25"><c r="A1" s="2" t="s"><v>1</v></c><c r="B1" s="3" t="s"><v>400</v></c><c r="C1" s="3" t="s"><v>401</v></c><c r="D1" s="3" t="s"><v>402</v></c><c r="E1" s="3" t="s"><v>403</v></c><c r="F1" s="5" t="s"><v>332</v></c><c r="G1" s="5" t="s"><v>381</v></c></row></sheetData><sortState ref="A1:G1"><sortCondition ref="A1"/><sortCondition ref="B1"/></sortState><pageMargins left="0.7" right="0.7" top="0.75" bottom="0.75" header="0.3" footer="0.3"/><tableParts count="1"><tablePart r:id="rId1"/></tableParts></worksheet>